moduleprofiler/__init__.py
moduleprofiler/io_size.py
moduleprofiler/logger.py
moduleprofiler/ops.py
moduleprofiler/profiler.py
moduleprofiler/utils.py
moduleprofiler-0.0.4.dist-info/LICENSE
moduleprofiler-0.0.4.dist-info/WHEEL
moduleprofiler-0.0.4.dist-info/METADATA
moduleprofiler-0.0.4.dist-info/RECORD
