Metadata-Version: 2.1
Name: moduleprofiler
Version: 0.0.4
Summary: Module profiler
Keywords: pytorch,machine-learning,neural-network,profiling,complexity-analysis
Author-email: Esteban Gómez <esteban.gomezmellado@aalto.fi>
Requires-Python: >=3.9
Requires-Dist: torch >= 2.3.0
Requires-Dist: pandas >= 2.0.0
Requires-Dist: psutil >= 6.0.0
Requires-Dist: tqdm >= 4.66.5
Requires-Dist: mkdocs>=1.6.0 ; extra == "docs"
Requires-Dist: mkdocstrings-python>=1.10.8 ; extra == "docs"
Requires-Dist: mkdocs-material>=9.5.31 ; extra == "docs"
Requires-Dist: ruff>=0.1.9 ; extra == "lint"
Requires-Dist: pytest>=7.4.3 ; extra == "test"
Project-URL: Bug Tracker, https://github.com/eagomez2/moduleprofiler/issues
Project-URL: Changelog, https://github.com/eagomez2/moduleprofiler/releases
Project-URL: Documentation, https://eagomez2.github.io/moduleprofiler/
Project-URL: Home, https://github.com/eagomez2/moduleprofiler
Project-URL: Repository, https://github.com/eagomez2/moduleprofiler
Provides-Extra: docs
Provides-Extra: lint
Provides-Extra: test
